README.md
setup.cfg
setup.py
dobg/__init__.py
dobg/dobg.py
dobg.egg-info/PKG-INFO
dobg.egg-info/SOURCES.txt
dobg.egg-info/dependency_links.txt
dobg.egg-info/entry_points.txt
dobg.egg-info/requires.txt
dobg.egg-info/top_level.txt
dobg/commands/__init__.py
dobg/commands/createdroplet.py
dobg/commands/deletedroplet.py
dobg/commands/listdroplets.py
dobg/commands/listimages.py
dobg/commands/listsizes.py
dobg/commands/powerondroplet.py
dobg/commands/settoken.py
dobg/commands/shutdowndroplet.py
dobg/exceptions/__init__.py
dobg/exceptions/configexceptions.py
dobg/exceptions/dropletexceptions.py
dobg/helper/__init__.py
dobg/helper/confighandler.py
dobg/helper/exceptionhandler.py