Metadata-Version: 2.1
Name: dobg
Version: 0.0.23
Summary: Digital Ocean CLI tool for managing Droplets
Home-page: https://github.com/markolat/dobgcli
Author: Marko Latinovic
Author-email: markolat@outlook.com
License: UNKNOWN
Platform: UNKNOWN
Classifier: Programming Language :: Python :: 3
Classifier: License :: Freely Distributable
Classifier: Operating System :: OS Independent
